qrshare/__init__.py
qrshare/__main__.py
qrshare/app.py
qrshare/auth.py
qrshare/meta.py
qrshare/search.py
qrshare/shortcut.py
qrshare/client/.gitignore
qrshare/client/README.md
qrshare/client/package.json
qrshare/client/rollup.config.js
qrshare/client/yarn.lock
qrshare/client/public/error.jinja2
qrshare/client/public/global.css
qrshare/client/public/index.jinja2
qrshare/client/public/login.html
qrshare/client/public/normalize.css
qrshare/client/public/skeleton.css
qrshare/client/public/build/error/bundle.css
qrshare/client/public/build/error/bundle.js
qrshare/client/public/build/error/bundle.js.map
qrshare/client/public/build/login/bundle.css
qrshare/client/public/build/login/bundle.js
qrshare/client/public/build/login/bundle.js.map
qrshare/client/public/build/main/bundle.css
qrshare/client/public/build/main/bundle.js
qrshare/client/public/build/main/bundle.js.map
qrshare/client/src/request.js
qrshare/client/src/components/BaseApp.svelte
qrshare/client/src/components/index.js
qrshare/client/src/components/list/ButtonGroup.svelte
qrshare/client/src/components/list/ListGroup.svelte
qrshare/client/src/components/list/ListTile.svelte
qrshare/client/src/components/list/SwitchGroup.svelte
qrshare/client/src/components/list/SwitchListTIle.svelte
qrshare/client/src/components/list/index.js
qrshare/client/src/components/navigation/ActionBar.svelte
qrshare/client/src/components/navigation/AppBar.svelte
qrshare/client/src/components/navigation/BottomNavigationBar.svelte
qrshare/client/src/components/navigation/NavigationElements.svelte
qrshare/client/src/components/navigation/index.js
qrshare/client/src/components/progressbars/HorizontalProgress.svelte
qrshare/client/src/components/progressbars/index.js
qrshare/client/src/helper/dom.js
qrshare/client/src/helper/index.js
qrshare/client/src/helper/misc.js
qrshare/client/src/helper/search.js
qrshare/client/src/module/icons/App.svelte
qrshare/client/src/module/icons/CaretLeftSquare.svelte
qrshare-0.4.0.dist-info/LICENSE
qrshare-0.4.0.dist-info/METADATA
qrshare-0.4.0.dist-info/WHEEL
qrshare-0.4.0.dist-info/entry_points.txt
qrshare-0.4.0.dist-info/top_level.txt
qrshare-0.4.0.dist-info/RECORD
