Metadata-Version: 2.1
Name: qrshare
Version: 0.4.0
Summary: flask waitress svelte file share program
Home-page: https://github.com/mHaisham/qrshare
Author: Schicksal
Author-email: mhaisham79@gmail.com
License: MIT license
Project-URL: Source code, https://github.com/mHaisham/qrshare
Keywords: qr share localhost
Platform: UNKNOWN
Classifier: License :: OSI Approved :: MIT License
Classifier: Programming Language :: Python :: 3.8
Classifier: Operating System :: OS Independent
Requires-Python: >=3.6
Requires-Dist: click (==7.1.2)
Requires-Dist: Flask (==1.1.2)
Requires-Dist: qrcode (==6.1)
Requires-Dist: waitress (==1.4.4)
Requires-Dist: appdirs (>=1.4.4)
